dotify/__init__.py
dotify/_decorators.py
dotify/_dotify.py
dotify/_json_serializable.py
dotify/_model.py
dotify/models/__init__.py
dotify/models/_album.py
dotify/models/_artist.py
dotify/models/_image.py
dotify/models/_playlist.py
dotify/models/_track.py
dotify/models/_user.py
dotify/models/schema/album.json
dotify/models/schema/artist.json
dotify/models/schema/image.json
dotify/models/schema/playlist.json
dotify/models/schema/track.json
dotify/models/schema/user.json
dotify/py.typed
dotify-2.0.6.dist-info/LICENSE
dotify-2.0.6.dist-info/WHEEL
dotify-2.0.6.dist-info/METADATA
dotify-2.0.6.dist-info/RECORD
