Metadata-Version: 2.1
Name: dotify
Version: 2.0.6
Summary: 🐍🎶 Yet another Spotify Web API Python library
Home-page: https://the-dotify-project.github.io/dotify
License: MIT
Keywords: spotify,download,downloader,youtube,mp3
Author: billsioros
Author-email: billsioros97@gmail.com
Requires-Python: >=3.7,<4.0
Classifier: Intended Audience :: Developers
Classifier: License :: OSI Approved :: MIT License
Classifier: Natural Language :: English
Classifier: Operating System :: OS Independent
Classifier: Programming Language :: Python
Classifier: Programming Language :: Python :: 3
Classifier: Programming Language :: Python :: 3 :: Only
Classifier: Programming Language :: Python :: 3.6
Classifier: Programming Language :: Python :: 3.7
Classifier: Programming Language :: Python :: 3.8
Classifier: Programming Language :: Python :: 3.9
Classifier: Topic :: Multimedia :: Sound/Audio
Requires-Dist: cached-property (>=1.5.2,<2.0.0)
Requires-Dist: coverage[toml] (>=5.5,<6.0)
Requires-Dist: moviepy
Requires-Dist: mutagen
Requires-Dist: python-jsonschema-objects
Requires-Dist: pytube
Requires-Dist: requests
Requires-Dist: spotipy
Requires-Dist: youtube-search-python
Project-URL: Bug Tracker, https://github.com/the-dotify-project/dotify/issues
Project-URL: Changelog, https://github.com/the-dotify-project/dotify/releases
Project-URL: Repository, https://github.com/the-dotify-project/dotify
